{
	"manufacturer": "Domitech Products, LLC",
	"manufacturerId": "0x020e",
	"label": "ZRKSW",
	"description": "Smart LED Light Bulb",
	"devices": [
		{
			"productType": "0x4c42",
			"productId": "0x3133",
			"zwaveAllianceId": 1443
		}
	],
	"firmwareVersion": {
		"min": "0.0",
		"max": "255.255"
	},
	"paramInformation": [
		{
			"#": "1",
			"label": "Dim Level When Powered On",
			"valueSize": 1,
			"defaultValue": 0,
			"allowManualEntry": false,
			"options": [
				{
					"label": "Full brightness",
					"value": 0
				},
				{
					"label": "Last dim level",
					"value": 1
				}
			]
		},
		{
			"#": "9",
			"label": "Dim Step Level",
			"description": "Defines the number of steps necessary to reach full brightness.",
			"valueSize": 1,
			"minValue": 1,
			"maxValue": 99,
			"defaultValue": 1
		},
		{
			"#": "10",
			"label": "Dim Step Timing",
			"description": "Timing of steps",
			"valueSize": 1,
			"minValue": 1,
			"maxValue": 10,
			"defaultValue": 3
		}
	],
	"metadata": {
		"inclusion": "1. Turn off power to the light bulb socket\n2. Screw in the light bulb\n3. Turn on power to the light bulb\n4. If successful, the LED light bulb will flash twice",
		"exclusion": "Turn off power to the light bulb socket, then turn on power to the light bulb. If successful, the LED light bulb will flash twice.",
		"reset": "Flick the wall switch 'OFF-ON' 4 times within 4 seconds. The light bulb will flash twice after reset is successful."
	}
}
